Metadata-Version: 2.4
Name: cellsampler
Version: 1.0.0
Summary: ""
Home-page: https://gitlab.developers.cam.ac.uk/astronomy/camcead/imaxt/cellsampler
Author: attr: cellsampler.__author__
Author-email: ""
License: "Apache License 2.0"
Project-URL: Bug Tracker, https://gitlab.developers.cam.ac.uk/astronomy/camcead/imaxt/cellsampler/-/issues
Classifier: Development Status :: 4 - Beta
Classifier: Programming Language :: Python
Classifier: Programming Language :: Python :: 3
Classifier: Programming Language :: Python :: 3.7
Classifier: Programming Language :: Python :: 3.8
Classifier: Programming Language :: Python :: 3.9
Classifier: Programming Language :: Python :: 3.10
Classifier: License :: OSI Approved :: MIT License
Classifier: Operating System :: OS Independent
Requires-Python: >=3.7
Requires-Dist: dask==2024.5.0
Requires-Dist: geocontour==1.3.1
Requires-Dist: matplotlib==3.8.4
Requires-Dist: numpy==1.23.5
Requires-Dist: pandas==2.2.2
Requires-Dist: scikit-image
Requires-Dist: scikit-learn==1.4.2
Requires-Dist: scipy==1.13.0
Requires-Dist: tifffile==2024.5.10
Requires-Dist: xarray==2024.5.0
Requires-Dist: zarr==2.18.0
Requires-Dist: cv2geojson
Provides-Extra: all
Requires-Dist: cellpose==3.0.8; extra == "all"
Requires-Dist: stardist==0.9.1; extra == "all"
Requires-Dist: DeepCell==0.12.10; extra == "all"
Provides-Extra: cellpose
Requires-Dist: cellpose==3.0.8; extra == "cellpose"
Provides-Extra: stardist
Requires-Dist: stardist==0.9.1; extra == "stardist"
Provides-Extra: deepcell
Requires-Dist: DeepCell==0.12.10; extra == "deepcell"
